odoo/addons/website_sale_product_sort/README.rst
odoo/addons/website_sale_product_sort/__init__.py
odoo/addons/website_sale_product_sort/__manifest__.py
odoo/addons/website_sale_product_sort/controllers/__init__.py
odoo/addons/website_sale_product_sort/controllers/main.py
odoo/addons/website_sale_product_sort/i18n/ca.po
odoo/addons/website_sale_product_sort/i18n/es.po
odoo/addons/website_sale_product_sort/i18n/fr.po
odoo/addons/website_sale_product_sort/i18n/nl.po
odoo/addons/website_sale_product_sort/i18n/website_sale_product_sort.pot
odoo/addons/website_sale_product_sort/migrations/13.0.1.0.0/post-migration.py
odoo/addons/website_sale_product_sort/models/__init__.py
odoo/addons/website_sale_product_sort/models/res_config_settings.py
odoo/addons/website_sale_product_sort/models/website.py
odoo/addons/website_sale_product_sort/readme/CONFIGURE.rst
odoo/addons/website_sale_product_sort/readme/CONTRIBUTORS.rst
odoo/addons/website_sale_product_sort/readme/DESCRIPTION.rst
odoo/addons/website_sale_product_sort/readme/ROADMAP.rst
odoo/addons/website_sale_product_sort/readme/USAGE.rst
odoo/addons/website_sale_product_sort/static/description/icon.png
odoo/addons/website_sale_product_sort/static/description/index.html
odoo/addons/website_sale_product_sort/views/res_config_settings_view.xml
odoo/addons/website_sale_product_sort/views/website_sale_sort.xml
odoo13_addon_website_sale_product_sort-13.0.1.0.2.dist-info/METADATA
odoo13_addon_website_sale_product_sort-13.0.1.0.2.dist-info/WHEEL
odoo13_addon_website_sale_product_sort-13.0.1.0.2.dist-info/top_level.txt
odoo13_addon_website_sale_product_sort-13.0.1.0.2.dist-info/RECORD
